sagemode/__init__.py
sagemode/DeploymentStateMachine/DeploymentStateMachine.py
sagemode/DeploymentStateMachine/__init__.py
sagemode/Helpers/FileCopy.py
sagemode/Helpers/SSHConnect.py
sagemode/Helpers/TypeChecking.py
sagemode/Helpers/UploadToRemote.py
sagemode/Helpers/WriteFunctionToFile.py
sagemode/Helpers/__init__.py
sagemode/InferenceFiles/__init__.py
sagemode/InferenceFiles/HFSageMaker/AutoModelForCausalLM.py
sagemode/InferenceFiles/HFSageMaker/AutoModelForSeq2SeqLM.py
sagemode/InferenceFiles/HFSageMaker/StableDiffusionPipeline.py
sagemode/InferenceFiles/HFSageMaker/__init__.py
sagemode/InferenceFiles/PyTorchEC2/__init__.py
sagemode/InferenceFiles/PyTorchEC2/server/__init__.py
sagemode/InferenceFiles/PyTorchEC2/server/main.py
sagemode/InferenceFiles/PyTorchSageMaker/PyTorchSageMaker.py
sagemode/InferenceFiles/PyTorchSageMaker/__init__.py
sagemode/LambdaFunctions/__init__.py
sagemode/LambdaFunctions/EC2/EC2.py
sagemode/LambdaFunctions/EC2/__init__.py
sagemode/LambdaFunctions/Sagemaker/Sagemaker.py
sagemode/LambdaFunctions/Sagemaker/__init__.py
sagemode/ResourceUser/HFSageMakerResourceUser.py
sagemode/ResourceUser/PyTorchEC2ResourceUser.py
sagemode/ResourceUser/PyTorchSageMakerResourceUser.py
sagemode/ResourceUser/ResourceUser.py
sagemode/ResourceUser/__init__.py
sagemode/ResourceUser/LambdaResourceUser/EC2LambdaResourceUser.py
sagemode/ResourceUser/LambdaResourceUser/SageMakerLambdaResourceUser.py
sagemode/ResourceUser/LambdaResourceUser/__init__.py
sagemode/Types/Arn.py
sagemode/Types/HFModels.py
sagemode/Types/IO.py
sagemode/Types/__init__.py
sagemode-0.1.0.dist-info/LICENSE
sagemode-0.1.0.dist-info/METADATA
sagemode-0.1.0.dist-info/WHEEL
sagemode-0.1.0.dist-info/top_level.txt
sagemode-0.1.0.dist-info/RECORD
