Metadata-Version: 2.1
Name: sagemode
Version: 0.1.0
Summary: Deploy, scale, and monitor your ML models all with one click. Native to AWS.
Home-page: UNKNOWN
Author: MDK8888
License: Apache License 2.0
Platform: UNKNOWN
License-File: LICENSE
Requires-Dist: accelerate ==0.25.0
Requires-Dist: annotated-types ==0.6.0
Requires-Dist: anyio ==4.2.0
Requires-Dist: arnparse ==0.0.2
Requires-Dist: attrs ==23.1.0
Requires-Dist: bcrypt ==4.1.2
Requires-Dist: bitsandbytes ==0.37.0
Requires-Dist: boto3 ==1.28.77
Requires-Dist: botocore ==1.31.77
Requires-Dist: certifi ==2023.7.22
Requires-Dist: cffi ==1.16.0
Requires-Dist: charset-normalizer ==3.3.2
Requires-Dist: click ==8.1.7
Requires-Dist: cloudpickle ==2.2.1
Requires-Dist: colorama ==0.4.6
Requires-Dist: contextlib2 ==21.6.0
Requires-Dist: cryptography ==41.0.7
Requires-Dist: diffusers ==0.24.0
Requires-Dist: dill ==0.3.7
Requires-Dist: dnspython ==2.4.2
Requires-Dist: email-validator ==2.1.0.post1
Requires-Dist: exceptiongroup ==1.2.0
Requires-Dist: fastapi ==0.108.0
Requires-Dist: filelock ==3.13.1
Requires-Dist: fsspec ==2023.10.0
Requires-Dist: google-pasta ==0.2.0
Requires-Dist: h11 ==0.14.0
Requires-Dist: hf-transfer ==0.1.3
Requires-Dist: httpcore ==1.0.2
Requires-Dist: httptools ==0.6.1
Requires-Dist: httpx ==0.26.0
Requires-Dist: huggingface-hub ==0.20.1
Requires-Dist: idna ==3.4
Requires-Dist: importlib-metadata ==6.8.0
Requires-Dist: itsdangerous ==2.1.2
Requires-Dist: Jinja2 ==3.1.2
Requires-Dist: jmespath ==1.0.1
Requires-Dist: jsonschema ==4.19.2
Requires-Dist: jsonschema-specifications ==2023.7.1
Requires-Dist: MarkupSafe ==2.1.3
Requires-Dist: mpmath ==1.3.0
Requires-Dist: multiprocess ==0.70.15
Requires-Dist: networkx ==3.2.1
Requires-Dist: numpy ==1.26.1
Requires-Dist: orjson ==3.9.10
Requires-Dist: packaging ==23.2
Requires-Dist: pandas ==2.1.2
Requires-Dist: paramiko ==3.4.0
Requires-Dist: pathos ==0.3.1
Requires-Dist: Pillow ==10.1.0
Requires-Dist: platformdirs ==3.11.0
Requires-Dist: pox ==0.3.3
Requires-Dist: ppft ==1.7.6.7
Requires-Dist: protobuf ==4.25.0
Requires-Dist: psutil ==5.9.6
Requires-Dist: pycparser ==2.21
Requires-Dist: pydantic ==2.5.2
Requires-Dist: pydantic-extra-types ==2.2.0
Requires-Dist: pydantic-settings ==2.1.0
Requires-Dist: pydantic-core ==2.14.5
Requires-Dist: PyNaCl ==1.5.0
Requires-Dist: python-dateutil ==2.8.2
Requires-Dist: python-dotenv ==1.0.0
Requires-Dist: python-multipart ==0.0.6
Requires-Dist: pytz ==2023.3.post1
Requires-Dist: PyYAML ==6.0.1
Requires-Dist: referencing ==0.30.2
Requires-Dist: regex ==2023.10.3
Requires-Dist: requests ==2.31.0
Requires-Dist: rpds-py ==0.10.6
Requires-Dist: s3transfer ==0.7.0
Requires-Dist: safetensors ==0.4.1
Requires-Dist: sagemaker ==2.196.0
Requires-Dist: schema ==0.7.5
Requires-Dist: six ==1.16.0
Requires-Dist: smdebug-rulesconfig ==1.0.1
Requires-Dist: sniffio ==1.3.0
Requires-Dist: starlette ==0.32.0.post1
Requires-Dist: sympy ==1.12
Requires-Dist: tblib ==1.7.0
Requires-Dist: tokenizers ==0.13.3
Requires-Dist: torch ==2.1.2
Requires-Dist: torchvision ==0.16.2
Requires-Dist: tqdm ==4.66.1
Requires-Dist: transformers ==4.26.0
Requires-Dist: typing-extensions ==4.8.0
Requires-Dist: tzdata ==2023.3
Requires-Dist: ujson ==5.9.0
Requires-Dist: urllib3 ==2.0.7
Requires-Dist: uvicorn ==0.25.0
Requires-Dist: watchfiles ==0.21.0
Requires-Dist: websockets ==12.0
Requires-Dist: zipp ==3.17.0
